README.md
pyproject.toml
setup.cfg
setup.py
src/probcox/__init__.py
src/probcox/probcox.py
src/probcox/simulation.py
src/probcox.egg-info/PKG-INFO
src/probcox.egg-info/SOURCES.txt
src/probcox.egg-info/dependency_links.txt
src/probcox.egg-info/requires.txt
src/probcox.egg-info/top_level.txt