Metadata-Version: 2.1
Name: probcox
Version: 0.0.3
Summary: Probilistic Cox Regression
Home-page: https://github.com/alexwjung/ProbCox
Author: Alexander Wolfgang Jung
Author-email: alex.w.jung@googlemail.com
License: UNKNOWN
Project-URL: Bug Tracker, https://github.com/alexwjung/ProbCox/issues
Platform: UNKNOWN
Classifier: Programming Language :: Python :: 3
Classifier: License :: OSI Approved :: MIT License
Classifier: Operating System :: OS Independent
Requires-Python: >=3.6
